src/data_memory.sv
//==============================================================================
// data_memory.sv
//
// Storage for LW/SW. This project's instruction subset only ever loads or
// stores a full 32-bit word at a time (no LB/LH/byte-level access), so --
// just like instruction_memory.sv -- the address coming in is a byte
// address, but storage internally is indexed one slot per word.
//==============================================================================

module data_memory #(
    parameter MEM_DEPTH_WORDS = 256
) (
    input  logic        clk,
    input  logic [31:0] addr,         // byte memory address (from the ALU: rs1 + imm)
    input  logic [31:0] write_data,   // value to store (SW only)
    input  logic        mem_read,
    input  logic        mem_write,
    output logic [31:0] read_data
);

  logic [31:0] mem [0:MEM_DEPTH_WORDS-1];

// Reset memory to zero
  initial begin
    for (int i = 0; i < MEM_DEPTH_WORDS; i++) begin
      mem[i] = 32'd0;
    end
  end

  // Reads are combinational. If mem_read isn't asserted this cycle, the
  // value just isn't used by anything downstream -- no harm driving it unconditionally.
  assign read_data = mem[addr[31:2]]; // byte address, so word index is addr[31:2]

  always_ff @(posedge clk) begin
    if (mem_write) begin
      mem[addr[31:2]] <= write_data;
    end
  end

endmodule

src/alu.sv
//==============================================================================
// Combinational ALU for the single-cycle / pipelined RV32I-subset processor.
// Implements the 4 operations this project's ISA actually needs:
//   ADD  -> ADD, ADDI, and address calculation for LW/SW
//   SUB  -> SUB, and BEQ comparison (rs1 - rs2; branch taken when zero == 1)
//   AND  -> AND
//   OR   -> OR
//
// This module only computes -- it has no idea what instruction is running.
//==============================================================================

module alu (
    input  logic [31:0] operand_a,   // first number (always rs1)
    input  logic [31:0] operand_b,   // second number (rs2, or an immediate)
    input  logic [1:0]  alu_op,      // select operations
 
    output logic [31:0] result,      
    output logic        zero         // 1 if result is exactly 0, else 0 (for BEQ and EX)
);

  localparam logic [1:0] ALU_ADD = 2'b00;   // 00 = add
  localparam logic [1:0] ALU_SUB = 2'b01;   // 01 = subtract
  localparam logic [1:0] ALU_AND = 2'b10;   // 10 = bitwise AND
  localparam logic [1:0] ALU_OR  = 2'b11;   // 11 = bitwise OR
 
  always_comb begin
    unique case (alu_op)
      ALU_ADD: result = operand_a + operand_b;  
      ALU_SUB: result = operand_a - operand_b;   
      ALU_AND: result = operand_a & operand_b;   
      ALU_OR:  result = operand_a | operand_b;   
 
      default: result = 32'd0;
    endcase
  end
 
  assign zero = (result == 32'd0);
 
endmodule

src/imm_generator.sv
//==============================================================================
// imm_generator.sv
//
// RISC-V has alot of different instruction formats, and this module is used
// to look at the opcode, figure out the format, and put the value back as a 32
// bit value.
// Used between the modules.
//==============================================================================

module imm_generator (
    input  logic [31:0] instruction,
    output logic [31:0] imm_out    // feeds into the ALU-source mux as one of two candidates for the ALU's second operand.
);

  logic [6:0]  opcode;
  logic        sign_bit;     // instruction[31] -- the universal sign bit
  logic [11:0] i_imm_bits;   // instruction[31:20], I-type
  logic [6:0]  s_imm_hi;     // instruction[31:25], S-type
  logic [4:0]  s_imm_lo;     // instruction[11:7],  S-type
  logic        b_imm_11;     // instruction[7],     B-type
  logic [5:0]  b_imm_10_5;   // instruction[30:25], B-type
  logic [3:0]  b_imm_4_1;    // instruction[11:8],  B-type

  assign opcode     = instruction[6:0];
  assign sign_bit   = instruction[31];
  assign i_imm_bits = instruction[31:20];
  assign s_imm_hi   = instruction[31:25];
  assign s_imm_lo   = instruction[11:7];
  assign b_imm_11   = instruction[7];
  assign b_imm_10_5 = instruction[30:25];
  assign b_imm_4_1  = instruction[11:8];

  localparam logic [6:0] OPC_RTYPE  = 7'b0110011;   // ADD/SUB/AND/OR -- no immediate
  localparam logic [6:0] OPC_ADDI   = 7'b0010011;   // I-type
  localparam logic [6:0] OPC_LOAD   = 7'b0000011;   // I-type (LW)
  localparam logic [6:0] OPC_STORE  = 7'b0100011;   // S-type (SW)
  localparam logic [6:0] OPC_BRANCH = 7'b1100011;   // B-type (BEQ)

  always_comb begin
    unique case (opcode)

      OPC_ADDI, OPC_LOAD: begin
        // I-type: a contiguous 12-bit immediate -- just sign-extend it.
        imm_out = {{20{sign_bit}}, i_imm_bits};
      end

      OPC_STORE: begin
        // S-type: the 12-bit immediate is split into two pieces because
        // the destination register field (rd) was repurposed to hold the
        // bottom half instead -- S-type instructions don't have a
        // destination register, so that field was free to reuse. Glue
        // the two pieces back together in the right order, then
        // sign-extend.
        imm_out = {{20{sign_bit}}, s_imm_hi, s_imm_lo};
      end

      OPC_BRANCH: begin
        // B-type: the most scrambled one. The immediate bits are
        // deliberately rearranged so the sign bit always lands in
        // instruction[31] regardless of format, keeping the
        // sign-extension hardware identical across every format. Bit 0
        // of a branch offset is never stored at all -- it's always 0
        // (branch targets are always an even number of bytes away) -- so
        // a literal 0 is tacked on instead of being read from anywhere.
        imm_out = {{19{sign_bit}}, sign_bit, b_imm_11, b_imm_10_5, b_imm_4_1, 1'b0};
      end

      default: begin
        // R-type (and anything unrecognized): no immediate is used here,
        // so the value is irrelevant. Zero is a harmless default.
        imm_out = 32'd0;
      end

    endcase
  end

endmodule

src/register_file.sv
//==============================================================================
// register_file.sv
//
// The CPU's 32 general-purpose registers (x0-x31), each 32 bits wide.
//
// Two things make this more than a plain array:
//   1. x0 is hardwired to zero -- reading it always returns 0, and writes
//      to it are silently thrown away. This is a RISC-V architectural rule,
//      not a choice this design makes.
//   2. "Write-read bypass": if something writes to a register on the same
//      clock edge that something else is reading that same register, the
//      read returns the NEW value being written, not the old stored one.
//      Single-cycle doesn't strictly need this (only one instruction is
//      ever active at a time), but it matters once you pipeline -- it lets
//      WB (writing back register N) and ID (reading register N) happen on
//      the same clock edge for two different instructions without needing
//      extra hazard-handling logic. Building it in now means Phase 4 has
//      one less hazard case to worry about.
//==============================================================================

module register_file (
    input  logic        clk,

    input  logic [4:0]  rs1_addr,   // which register to read (source 1)
    input  logic [4:0]  rs2_addr,   // which register to read (source 2)
    output logic [31:0] rs1_data,
    output logic [31:0] rs2_data,

    input  logic [4:0]  rd_addr,    // which register to write
    input  logic [31:0] rd_data,    // value to write
    input  logic        reg_write   // write enable
);

  logic [31:0] regs [0:31];

  // Simulation-only startup value -- without this, an unwritten register
  // would read back as 'X' (unknown) the first time something reads it,
  // which makes early debugging confusing for no good reason.
  initial begin
    for (int i = 0; i < 32; i++) begin
      regs[i] = 32'd0;
    end
  end

  // Reads: combinational (no clock needed -- the value is just there)
  always_comb begin
    if (rs1_addr == 5'd0)
      rs1_data = 32'd0;
    else if (reg_write && (rd_addr == rs1_addr))
      rs1_data = rd_data;            // write-read bypass
    else
      rs1_data = regs[rs1_addr];

    if (rs2_addr == 5'd0)
      rs2_data = 32'd0;
    else if (reg_write && (rd_addr == rs2_addr))
      rs2_data = rd_data;            // write-read bypass
    else
      rs2_data = regs[rs2_addr];
  end

  // Write: synchronous, on the rising clock edge
  always_ff @(posedge clk) begin
    if (reg_write && (rd_addr != 5'd0)) begin
      regs[rd_addr] <= rd_data;
    end
  end

endmodule

src/control_unit.sv
//==============================================================================
// control_unit.sv
//
// Looks at WHICH instruction is currently being executed (its opcode,
// funct3, and one bit of funct7), and decides how every other module in
// the datapath should behave.
//==============================================================================

module control_unit (
    input  logic [6:0] opcode,      // instruction[6:0] (what type of operations is this ?)
    input  logic [2:0] funct3,      // instruction[14:12] (Mathematical/AND/OR)
    input  logic       funct7_5,    // instruction[30] -- distinguishes ADD (0) from SUB (1)

    output logic [1:0] alu_op,      // ALU operation option. Tells which operation to perform
    output logic       reg_write,   // 1 = write the result of the ALU to the register file, 0 = don't write
    output logic       mem_read,    // 1 = read from data memory, 0 = don't read from data memory
    output logic       mem_write,   // 1 = write to data memory, 0 = don't write to data memory
    output logic       mem_to_reg,  // selects write-back source: 1 = data memory, 0 = ALU result (only relevant when reg_write = 1)
    output logic       branch,      // A flag for when ALU is set to SUB
    output logic       alu_src      // 1 = ALU's 2nd operand is the output from imm_generator, 0 = it's the value from the register file
);

  localparam logic [6:0] OPC_RTYPE  = 7'b0110011;
  localparam logic [6:0] OPC_ADDI   = 7'b0010011;
  localparam logic [6:0] OPC_LOAD   = 7'b0000011;
  localparam logic [6:0] OPC_STORE  = 7'b0100011;
  localparam logic [6:0] OPC_BRANCH = 7'b1100011;

  localparam logic [1:0] ALU_ADD = 2'b00;
  localparam logic [1:0] ALU_SUB = 2'b01;
  localparam logic [1:0] ALU_AND = 2'b10;
  localparam logic [1:0] ALU_OR  = 2'b11;

  always_comb begin
    alu_op     = ALU_ADD;
    reg_write  = 1'b0;
    mem_read   = 1'b0;
    mem_write  = 1'b0;
    mem_to_reg = 1'b0;
    branch     = 1'b0;
    alu_src    = 1'b0;

    unique case (opcode)

      OPC_RTYPE: begin              // ADD / SUB / AND / OR
        reg_write = 1'b1;
        alu_src   = 1'b0;           // both ALU operands come from registers
        unique case (funct3)
          3'b000:  alu_op = funct7_5 ? ALU_SUB : ALU_ADD;
          3'b111:  alu_op = ALU_AND;
          3'b110:  alu_op = ALU_OR;
          default: alu_op = ALU_ADD;   // not reachable for this project's ISA subset
        endcase
      end

      OPC_ADDI: begin
        reg_write = 1'b1;
        alu_src   = 1'b1;           // 2nd operand is the immediate
        alu_op    = ALU_ADD;
      end

      OPC_LOAD: begin               // LW
        reg_write  = 1'b1;
        alu_src    = 1'b1;          // address = rs1 + immediate
        alu_op     = ALU_ADD;
        mem_read   = 1'b1;
        mem_to_reg = 1'b1;          // write-back value comes from memory
      end

      OPC_STORE: begin              // SW
        alu_src   = 1'b1;           // address = rs1 + immediate
        alu_op    = ALU_ADD;
        mem_write = 1'b1;
        // reg_write stays 0 -- SW never writes a register
      end

      OPC_BRANCH: begin             // BEQ
        alu_src = 1'b0;             // compare two register values directly
        alu_op  = ALU_SUB;          // subtract; ALU's zero flag means "equal"
        branch  = 1'b1;
        // reg_write stays 0 -- BEQ never writes a register
      end

      default: ; 

    endcase
  end

endmodule

src/instruction_memory.sv
//==============================================================================
// instruction_memory.sv
//
// Read-only program storage. The PC feeds in a byte address; this module
// hands back the 32-bit instruction sitting there.
//==============================================================================

module instruction_memory #(
    parameter MEM_DEPTH_WORDS = 256,        // how many instructions of ROM
    parameter INIT_FILE = "program.hex"     // hex file loaded at sim start
) (
    input  logic [31:0] addr,               // byte address (comes from PC)
    output logic [31:0] instruction
);

  logic [31:0] mem [0:MEM_DEPTH_WORDS-1];

  initial begin
    for (int i = 0; i < MEM_DEPTH_WORDS; i++) begin
      mem[i] = 32'h00000013;   // ADDI x0, x0, 0 == NOP
    end

    $readmemh(INIT_FILE, mem);
  end

  assign instruction = mem[addr[31:2]];

endmodule

src/pc_register.sv
//==============================================================================
// pc_register.sv
//
// Holds the address of the instruction currently being fetched, and
// decides what address comes next: normally PC+4 (the next instruction in
// sequence), unless a branch was just taken, in which case it's the
// branch target instead.
//==============================================================================

module pc_register (
    input  logic        clk,
    input  logic        branch_taken,    // from datapath.sv: Branch control bit AND the ALU's zero flag
    input  logic [31:0] branch_target,   // PC + branch immediate, computed in datapath.sv
    output logic [31:0] pc_current
);

  logic [31:0] pc_next;
  // if branch_taken is true, the it will take the value from the branch target
  assign pc_next = branch_taken ? branch_target : (pc_current + 32'd4);

  initial begin
    pc_current = 32'd0;   // every program starts executing at address 0
  end

  always_ff @(posedge clk) begin
    pc_current <= pc_next;
  end

endmodule

src/datapath.sv
//==============================================================================
// datapath.sv
//
// Wires every module above into the complete single-cycle datapath from
// the project plan's diagram: PC -> instruction memory -> decode ->
// {control unit, register file, immediate generator} -> ALU -> data
// memory -> write-back mux -> back into the register file, with the
// branch-target/PC+4 decision feeding back into the PC.
//
//==============================================================================

module datapath #(
    parameter INIT_FILE = "program.hex"
) (
    input logic clk
);

  // Program Counter
  logic [31:0] pc_current;
  logic        branch_taken;
  logic [31:0] branch_target;

  pc_register u_pc (
      .clk           (clk),
      .branch_taken  (branch_taken),
      .branch_target (branch_target),
      .pc_current    (pc_current)
  );

  // Instruction Fetch
  logic [31:0] instruction;

  instruction_memory #(
      .INIT_FILE (INIT_FILE)
  ) u_imem (
      .addr        (pc_current),
      .instruction (instruction)
  );

  // Instruction Decode: just field slicing, no separate module needed
  logic [6:0] opcode;
  logic [2:0] funct3;
  logic       funct7_5;
  logic [4:0] rs1_addr;
  logic [4:0] rs2_addr;
  logic [4:0] rd_addr;

  assign opcode   = instruction[6:0];
  assign funct3   = instruction[14:12];
  assign funct7_5 = instruction[30];
  assign rs1_addr = instruction[19:15];
  assign rs2_addr = instruction[24:20];
  assign rd_addr  = instruction[11:7];

  // Control Unit
  logic [1:0] alu_op;
  logic       reg_write, mem_read, mem_write, mem_to_reg, branch, alu_src;

  control_unit u_control (
      .opcode     (opcode),
      .funct3     (funct3),
      .funct7_5   (funct7_5),
      .alu_op     (alu_op),
      .reg_write  (reg_write),
      .mem_read   (mem_read),
      .mem_write  (mem_write),
      .mem_to_reg (mem_to_reg),
      .branch     (branch),
      .alu_src    (alu_src)
  );

  // Register File
  logic [31:0] rs1_data, rs2_data, write_back_data;

  register_file u_regfile (
      .clk       (clk),
      .rs1_addr  (rs1_addr),
      .rs2_addr  (rs2_addr),
      .rs1_data  (rs1_data),
      .rs2_data  (rs2_data),
      .rd_addr   (rd_addr),
      .rd_data   (write_back_data),
      .reg_write (reg_write)
  );

  // Immediate Generator
  logic [31:0] imm_out;

  imm_generator u_immgen (
      .instruction (instruction),
      .imm_out     (imm_out)
  );

  // ALU, with the ALUSrc mux feeding its 2nd operand
  logic [31:0] alu_operand_b;
  logic [31:0] alu_result;
  logic        alu_zero;

  assign alu_operand_b = alu_src ? imm_out : rs2_data;

  alu u_alu (
      .operand_a (rs1_data),
      .operand_b (alu_operand_b),
      .alu_op    (alu_op),
      .result    (alu_result),
      .zero      (alu_zero)
  );

  // Data Memory
  logic [31:0] mem_read_data;

  data_memory u_dmem (
      .clk        (clk),
      .addr       (alu_result),
      .write_data (rs2_data),
      .mem_read   (mem_read),
      .mem_write  (mem_write),
      .read_data  (mem_read_data)
  );

  // Write-Back mux: ALU result, or loaded memory data
  assign write_back_data = mem_to_reg ? mem_read_data : alu_result;

  assign branch_target = pc_current + imm_out;
  assign branch_taken  = branch && alu_zero; // check if branch condition is met

endmodule

tb/single_cycle_tb.sv
//==============================================================================
// single_cycle_tb.sv
//
// Phase 2 testbench: runs the datapath for comfortably more cycles
// than the test program needs, then prints final register and memory
// values so you can compare them against the expected-values table by
// eye. Also sets up waveform dumping for GTKWave.
//==============================================================================

`timescale 1ns/1ps

module single_cycle_tb;

  logic clk;

  datapath dut (
      .clk (clk)
  );

  // Free-running simulation clock. The period itself is arbitrary -- this
  // is a single-cycle design with no real timing constraints to meet.
  initial clk = 0;
  always #5 clk = ~clk;

  initial begin
    $dumpfile("waves.vcd");
    $dumpvars(0, single_cycle_tb);

    // The test program needs 13 clock edges to fully execute. Running 20
    // gives margin without depending on that count being razor-precise --
    // any extra cycles just execute harmless NOPs.
    repeat (20) @(posedge clk);

    $display("-----------------------------------------------");
    $display(" Final register values");
    $display("-----------------------------------------------");
    for (int i = 0; i <= 11; i++) begin
      $display(" x%0d = %0d (0x%08h)", i, dut.u_regfile.regs[i], dut.u_regfile.regs[i]);
    end
    $display("-----------------------------------------------");
    $display(" Mem[0] = %0d (0x%08h)", dut.u_dmem.mem[0], dut.u_dmem.mem[0]);
    $display("-----------------------------------------------");

    $finish;
  end

endmodule

waves.vcd
$date
	Wed Jul 01 03:10:17 2026
$end
$version
	Icarus Verilog
$end
$timescale
	1ps
$end
$scope module single_cycle_tb $end
$var reg 1 ! clk $end
$scope module dut $end
$var wire 1 " branch_taken $end
$var wire 1 ! clk $end
$var wire 32 # write_back_data [31:0] $end
$var wire 32 $ rs2_data [31:0] $end
$var wire 5 % rs2_addr [4:0] $end
$var wire 32 & rs1_data [31:0] $end
$var wire 5 ' rs1_addr [4:0] $end
$var wire 1 ( reg_write $end
$var wire 5 ) rd_addr [4:0] $end
$var wire 32 * pc_current [31:0] $end
$var wire 7 + opcode [6:0] $end
$var wire 1 , mem_write $end
$var wire 1 - mem_to_reg $end
$var wire 32 . mem_read_data [31:0] $end
$var wire 1 / mem_read $end
$var wire 32 0 instruction [31:0] $end
$var wire 32 1 imm_out [31:0] $end
$var wire 1 2 funct7_5 $end
$var wire 3 3 funct3 [2:0] $end
$var wire 32 4 branch_target [31:0] $end
$var wire 1 5 branch $end
$var wire 1 6 alu_zero $end
$var wire 1 7 alu_src $end
$var wire 32 8 alu_result [31:0] $end
$var wire 32 9 alu_operand_b [31:0] $end
$var wire 2 : alu_op [1:0] $end
$var parameter 88 ; INIT_FILE $end
$scope module u_alu $end
$var wire 32 < operand_b [31:0] $end
$var wire 1 6 zero $end
$var wire 32 = operand_a [31:0] $end
$var wire 2 > alu_op [1:0] $end
$var parameter 2 ? ALU_ADD $end
$var parameter 2 @ ALU_AND $end
$var parameter 2 A ALU_OR $end
$var parameter 2 B ALU_SUB $end
$var reg 32 C result [31:0] $end
$upscope $end
$scope module u_control $end
$var wire 3 D funct3 [2:0] $end
$var wire 1 2 funct7_5 $end
$var wire 7 E opcode [6:0] $end
$var parameter 2 F ALU_ADD $end
$var parameter 2 G ALU_AND $end
$var parameter 2 H ALU_OR $end
$var parameter 2 I ALU_SUB $end
$var parameter 7 J OPC_ADDI $end
$var parameter 7 K OPC_BRANCH $end
$var parameter 7 L OPC_LOAD $end
$var parameter 7 M OPC_RTYPE $end
$var parameter 7 N OPC_STORE $end
$var reg 2 O alu_op [1:0] $end
$var reg 1 7 alu_src $end
$var reg 1 5 branch $end
$var reg 1 / mem_read $end
$var reg 1 - mem_to_reg $end
$var reg 1 , mem_write $end
$var reg 1 ( reg_write $end
$upscope $end
$scope module u_dmem $end
$var wire 32 P addr [31:0] $end
$var wire 1 ! clk $end
$var wire 1 / mem_read $end
$var wire 1 , mem_write $end
$var wire 32 Q read_data [31:0] $end
$var wire 32 R write_data [31:0] $end
$var parameter 32 S MEM_DEPTH_WORDS $end
$scope begin $ivl_for_loop2 $end
$var integer 32 T i [31:0] $end
$upscope $end
$upscope $end
$scope module u_imem $end
$var wire 32 U instruction [31:0] $end
$var wire 32 V addr [31:0] $end
$var parameter 88 W INIT_FILE $end
$var parameter 32 X MEM_DEPTH_WORDS $end
$scope begin $ivl_for_loop1 $end
$var integer 32 Y i [31:0] $end
$upscope $end
$upscope $end
$scope module u_immgen $end
$var wire 32 Z instruction [31:0] $end
$var wire 1 [ sign_bit $end
$var wire 5 \ s_imm_lo [4:0] $end
$var wire 7 ] s_imm_hi [6:0] $end
$var wire 7 ^ opcode [6:0] $end
$var wire 12 _ i_imm_bits [11:0] $end
$var wire 4 ` b_imm_4_1 [3:0] $end
$var wire 1 a b_imm_11 $end
$var wire 6 b b_imm_10_5 [5:0] $end
$var parameter 7 c OPC_ADDI $end
$var parameter 7 d OPC_BRANCH $end
$var parameter 7 e OPC_LOAD $end
$var parameter 7 f OPC_RTYPE $end
$var parameter 7 g OPC_STORE $end
$var reg 32 h imm_out [31:0] $end
$upscope $end
$scope module u_pc $end
$var wire 1 " branch_taken $end
$var wire 32 i branch_target [31:0] $end
$var wire 1 ! clk $end
$var wire 32 j pc_next [31:0] $end
$var reg 32 k pc_current [31:0] $end
$upscope $end
$scope module u_regfile $end
$var wire 1 ! clk $end
$var wire 5 l rd_addr [4:0] $end
$var wire 32 m rd_data [31:0] $end
$var wire 1 ( reg_write $end
$var wire 5 n rs1_addr [4:0] $end
$var wire 5 o rs2_addr [4:0] $end
$var reg 32 p rs1_data [31:0] $end
$var reg 32 q rs2_data [31:0] $end
$scope begin $ivl_for_loop0 $end
$var integer 32 r i [31:0] $end
$upscope $end
$upscope $end
$upscope $end
$scope begin $ivl_for_loop3 $end
$var integer 32 s i [31:0] $end
$upscope $end
$upscope $end
$enddefinitions $end
$comment Show the parameter values. $end
$dumpall
b100011 g
b110011 f
b11 e
b1100011 d
b10011 c
b100000000 X
b111000001110010011011110110011101110010011000010110110100101110011010000110010101111000 W
b100000000 S
b100011 N
b110011 M
b11 L
b1100011 K
b10011 J
b1 I
b11 H
b10 G
b0 F
b1 B
b11 A
b10 @
b0 ?
b111000001110010011011110110011101110010011000010110110100101110011010000110010101111000 ;
$end
#0
$dumpvars
b0 s
b100000 r
b0 q
b0 p
b101 o
b0 n
b101 m
b1 l
b0 k
b100 j
b101 i
b101 h
b0 b
1a
b0 `
b101 _
b10011 ^
b0 ]
b1 \
0[
b10100000000000010010011 Z
b100000000 Y
b0 V
b10100000000000010010011 U
b100000000 T
b0 R
b0 Q
b101 P
b0 O
b10011 E
b0 D
b101 C
b0 >
b0 =
b101 <
b0 :
b101 9
b101 8
17
06
05
b101 4
b0 3
02
b101 1
b10100000000000010010011 0
0/
b0 .
0-
0,
b10011 +
b0 *
b1 )
1(
b0 '
b0 &
b101 %
b0 $
b101 #
0"
0!
$end
#5000
b11 #
b11 m
b11 8
b11 C
b11 P
b11 9
b11 <
b11 1
b11 h
b11 _
b10 \
0a
b1 `
b10 )
b10 l
b11 %
b11 o
b1000 j
b1100000000000100010011 0
b1100000000000100010011 U
b1100000000000100010011 Z
b111 4
b111 i
b100 *
b100 V
b100 k
1!
#10000
0!
#15000
b1000 #
b1000 m
b1000 8
b1000 C
b1000 P
b0 1
b0 h
b11 $
b11 R
b11 q
b101 &
b101 =
b101 p
07
1(
b110011 ^
b10 _
b11 \
1a
b11 )
b11 l
b10 %
b10 o
b1 '
b1 n
b110011 +
b110011 E
b1100 j
b1000001000000110110011 0
b1000001000000110110011 U
b1000001000000110110011 Z
b1000 4
b1000 i
b1000 *
b1000 V
b1000 k
1!
#20000
0!
#25000
b10 #
b10 m
b10 8
b10 C
b10 P
b1 :
b1 >
b1 O
1(
b10000000010 _
b100000 ]
b100 \
0a
b100000 b
b10 `
b100 )
b100 l
12
b10000 j
b1000000001000001000001000110011 0
b1000000001000001000001000110011 U
b1000000001000001000001000110011 Z
b1100 4
b1100 i
b1100 *
b1100 V
b1100 k
1!
#30000
0!
#35000
b1 #
b1 m
b1 8
b1 C
b1 P
1(
b10 :
b10 >
b10 O
b10 _
b0 ]
b101 \
1a
b0 b
b101 )
b101 l
02
b111 3
b111 D
b10100 j
b1000001111001010110011 0
b1000001111001010110011 U
b1000001111001010110011 Z
b10000 4
b10000 i
b10000 *
b10000 V
b10000 k
1!
#40000
0!
#45000
b111 #
b111 m
b111 8
b111 C
b111 P
1(
b11 :
b11 >
b11 O
b110 \
0a
b11 `
b110 )
b110 l
b110 3
b110 D
b11000 j
b1000001110001100110011 0
b1000001110001100110011 U
b1000001110001100110011 Z
b10100 4
b10100 i
b10100 *
b10100 V
b10100 k
1!
#50000
0!
#55000
16
b0 #
b0 m
b0 9
b0 <
b0 8
b0 C
b0 P
b1000 $
b1000 R
b1000 q
b0 &
b0 =
b0 p
1,
17
0(
b0 :
b0 >
b0 O
b100011 ^
b11 _
b0 \
b0 `
b0 )
b0 l
b11 %
b11 o
b0 '
b0 n
b10 3
b10 D
b100011 +
b100011 E
b11100 j
b1100000010000000100011 0
b1100000010000000100011 U
b1100000010000000100011 Z
b11000 4
b11000 i
b11000 *
b11000 V
b11000 k
1!
#60000
0!
#65000
b1000 #
b1000 m
b0 $
b0 R
b0 q
1-
1/
1(
17
0,
b11 ^
b0 _
b111 \
1a
b11 `
b111 )
b111 l
b0 %
b0 o
b11 +
b11 E
b100000 j
b10001110000011 0
b10001110000011 U
b10001110000011 Z
b11100 4
b11100 i
b11100 *
b11100 V
b11100 k
b1000 .
b1000 Q
1!
#70000
0!
#75000
1"
b1000 9
b1000 <
b0 #
b0 m
b1000 1
b1000 h
b1000 $
b1000 R
b1000 q
b1000 &
b1000 =
b1000 p
15
b1 :
b1 >
b1 O
07
0-
0/
0(
b1100011 ^
b111 _
b1000 \
0a
b100 `
b1000 )
b1000 l
b111 %
b111 o
b11 '
b11 n
b0 3
b0 D
b1100011 +
b1100011 E
b101000 j
b11100011000010001100011 0
b11100011000010001100011 U
b11100011000010001100011 Z
b101000 4
b101000 i
b100000 *
b100000 V
b100000 k
1!
#80000
0!
#85000
b0 .
b0 Q
b101010 #
b101010 m
b101010 9
b101010 <
0"
06
b101010 8
b101010 C
b101010 P
b101010 1
b101010 h
b0 $
b0 R
b0 q
b0 &
b0 =
b0 p
17
1(
05
b0 :
b0 >
b0 O
b10011 ^
b101010 _
b1 ]
b1001 \
1a
b1 b
b1001 )
b1001 l
b1010 %
b1010 o
b0 '
b0 n
b10011 +
b10011 E
b10101000000000010010010011 0
b10101000000000010010010011 U
b10101000000000010010010011 Z
b101100 j
b1010010 4
b1010010 i
b101000 *
b101000 V
b101000 k
1!
#90000
0!
#95000
b1000 .
b1000 Q
b10 #
b10 m
b10 8
b10 C
b10 P
b11 9
b11 <
b1000 1
b1000 h
b11 $
b11 R
b11 q
b101 &
b101 =
b101 p
15
b1 :
b1 >
b1 O
07
0(
b1100011 ^
b10 _
b0 ]
b1000 \
0a
b0 b
b1000 )
b1000 l
b10 %
b10 o
b1 '
b1 n
b1100011 +
b1100011 E
b110000 j
b1000001000010001100011 0
b1000001000010001100011 U
b1000001000010001100011 Z
b110100 4
b110100 i
b101100 *
b101100 V
b101100 k
1!
#100000
0!
#105000
b0 .
b0 Q
b1001101 #
b1001101 m
b1001101 9
b1001101 <
b1001101 8
b1001101 C
b1001101 P
b1001101 1
b1001101 h
b0 $
b0 R
b0 q
b0 &
b0 =
b0 p
17
1(
05
b0 :
b0 >
b0 O
b10011 ^
b1001101 _
b10 ]
b1010 \
b10 b
b101 `
b1010 )
b1010 l
b1101 %
b1101 o
b0 '
b0 n
b10011 +
b10011 E
b110100 j
b100110100000000010100010011 0
b100110100000000010100010011 U
b100110100000000010100010011 Z
b1111101 4
b1111101 i
b110000 *
b110000 V
b110000 k
1!
#110000
0!
#115000
b1011 #
b1011 m
b1011 8
b1011 C
b1011 P
b1011 9
b1011 <
b1011 1
b1011 h
b1011 $
b1011 R
b1011 q
b1011 _
b0 ]
b1011 \
1a
b0 b
b1011 )
b1011 l
b1011 %
b1011 o
b111000 j
b101100000000010110010011 0
b101100000000010110010011 U
b101100000000010110010011 Z
b111111 4
b111111 i
b110100 *
b110100 V
b110100 k
1!
#120000
0!
#125000
b1000 .
b1000 Q
b0 #
b0 m
16
b0 8
b0 C
b0 P
b0 9
b0 <
b0 1
b0 h
b0 $
b0 R
b0 q
b0 _
b0 \
0a
b0 `
b0 )
b0 l
b0 %
b0 o
b111100 j
b10011 0
b10011 U
b10011 Z
b111000 4
b111000 i
b111000 *
b111000 V
b111000 k
1!
#130000
0!
#135000
b1000000 j
b111100 4
b111100 i
b111100 *
b111100 V
b111100 k
1!
#140000
0!
#145000
b1000100 j
b1000000 4
b1000000 i
b1000000 *
b1000000 V
b1000000 k
1!
#150000
0!
#155000
b1001000 j
b1000100 4
b1000100 i
b1000100 *
b1000100 V
b1000100 k
1!
#160000
0!
#165000
b1001100 j
b1001000 4
b1001000 i
b1001000 *
b1001000 V
b1001000 k
1!
#170000
0!
#175000
b1010000 j
b1001100 4
b1001100 i
b1001100 *
b1001100 V
b1001100 k
1!
#180000
0!
#185000
b1010100 j
b1010000 4
b1010000 i
b1010000 *
b1010000 V
b1010000 k
1!
#190000
0!
#195000
b1011000 j
b1010100 4
b1010100 i
b1010100 *
b1010100 V
b1010100 k
b1100 s
1!
